migrations_mgmt_cmds/__init__.py
migrations_mgmt_cmds/storage.py
migrations_mgmt_cmds/management/__init__.py
migrations_mgmt_cmds/management/commands/__init__.py
migrations_mgmt_cmds/management/commands/migrations_release.py
migrations_mgmt_cmds/management/commands/migrations_rollback.py
migrations_mgmt_cmds/management/commands/release_management.py
django_migrations_mgmt-0.3.3.dist-info/LICENSE
django_migrations_mgmt-0.3.3.dist-info/METADATA
django_migrations_mgmt-0.3.3.dist-info/WHEEL
django_migrations_mgmt-0.3.3.dist-info/top_level.txt
django_migrations_mgmt-0.3.3.dist-info/RECORD
